{
	"addedLines": 662054,
	"deletedLines": 365939,
	"commits": 10271,
	"mergedPRs": 1478,
	"ciRuns": 5291,
	"lastUpdated": "2026-03-26T17:02:08.865Z",
	"languages": [
		{
			"id": "Go",
			"label": "Go",
			"value": 37,
			"color": "#e06952"
		},
		{
			"id": "Dart",
			"label": "Dart",
			"value": 21,
			"color": "#e0d552"
		},
		{
			"id": "TypeScript",
			"label": "TypeScript",
			"value": 15,
			"color": "#81e052"
		},
		{
			"id": "Ruby",
			"label": "Ruby",
			"value": 14,
			"color": "#52e08d"
		},
		{
			"id": "Python",
			"label": "Python",
			"value": 9,
			"color": "#52c9e0"
		},
		{
			"id": "JavaScript",
			"label": "JavaScript",
			"value": 2,
			"color": "#525ee0"
		},
		{
			"id": "Astro",
			"label": "Astro",
			"value": 1,
			"color": "#b152e0"
		},
		{
			"id": "Shell",
			"label": "Shell",
			"value": 1,
			"color": "#e052a5"
		}
	],
	"aiUsage": [],
	"aiTokens": 0,
	"ossPRs": 0
}
